keyboardkey/__init__.py
keyboardkey/keys.py
keyboardkey-3.0.dist-info/licenses/LICENSE.txt
keyboardkey-3.0.dist-info/METADATA
keyboardkey-3.0.dist-info/WHEEL
keyboardkey-3.0.dist-info/top_level.txt
keyboardkey-3.0.dist-info/RECORD
