Metadata-Version: 2.4
Name: keyboardkey
Version: 3.0
Summary: A module providing lists of real keyboard keys.
Author: Aaron Geo Reji
License: MIT
Keywords: keyboard,keys,python,keyboardkey,key
Requires-Python: >=3.7
License-File: LICENSE.txt
Dynamic: license-file
